streamlit_wordcloud/__init__.py
streamlit_wordcloud/streamlit_wordcloud.py
streamlit_wordcloud/utils.py
streamlit_wordcloud/frontend/build/asset-manifest.json
streamlit_wordcloud/frontend/build/bootstrap.min.css
streamlit_wordcloud/frontend/build/index.html
streamlit_wordcloud/frontend/build/precache-manifest.63d84cc948592c7dc0e6730b67272187.js
streamlit_wordcloud/frontend/build/service-worker.js
streamlit_wordcloud/frontend/build/static/css/2.2a9431d7.chunk.css
streamlit_wordcloud/frontend/build/static/css/2.2a9431d7.chunk.css.map
streamlit_wordcloud/frontend/build/static/js/2.2eaa678a.chunk.js
streamlit_wordcloud/frontend/build/static/js/2.2eaa678a.chunk.js.LICENSE.txt
streamlit_wordcloud/frontend/build/static/js/2.2eaa678a.chunk.js.map
streamlit_wordcloud/frontend/build/static/js/main.516c3972.chunk.js
streamlit_wordcloud/frontend/build/static/js/main.516c3972.chunk.js.map
streamlit_wordcloud/frontend/build/static/js/runtime-main.11ec9aca.js
streamlit_wordcloud/frontend/build/static/js/runtime-main.11ec9aca.js.map
streamlit_wordcloud-0.1.0.dist-info/LICENSE
streamlit_wordcloud-0.1.0.dist-info/METADATA
streamlit_wordcloud-0.1.0.dist-info/WHEEL
streamlit_wordcloud-0.1.0.dist-info/top_level.txt
streamlit_wordcloud-0.1.0.dist-info/RECORD
