Metadata-Version: 2.1
Name: streamlit-wordcloud
Version: 0.1.0
Summary: This is an interactive Wordcloud component for Streamlit. This is based on React-Wordcloud (https://github.com/chrisrzhou/react-wordcloud).
Home-page: https://github.com/rezaho/streamlit-wordcloud
Author: Reza Hosseini
Author-email: re1372@gmail.com
License: UNKNOWN
Platform: UNKNOWN
Requires-Python: >=3.6
